NetkillerDeveloper/README.md
NetkillerDeveloper/__init__.py
NetkillerDeveloper/__main__.py
NetkillerDeveloper/file.epub
NetkillerDeveloper/index.html
NetkillerDeveloper/css/__init__.py
NetkillerDeveloper/css/annotations.css
NetkillerDeveloper/css/main.css
NetkillerDeveloper/css/normalize.css
NetkillerDeveloper/css/popup.css
NetkillerDeveloper/font/__init__.py
NetkillerDeveloper/font/fontello.eot
NetkillerDeveloper/font/fontello.svg
NetkillerDeveloper/font/fontello.ttf
NetkillerDeveloper/font/fontello.woff
NetkillerDeveloper/img/__init__.py
NetkillerDeveloper/img/annotator-glyph-sprite.png
NetkillerDeveloper/img/annotator-icon-sprite.png
NetkillerDeveloper/img/apple-touch-icon.png
NetkillerDeveloper/img/cancelfullscreen.png
NetkillerDeveloper/img/close.png
NetkillerDeveloper/img/fullscreen.png
NetkillerDeveloper/img/loader.gif
NetkillerDeveloper/img/menu-icon.png
NetkillerDeveloper/img/save.png
NetkillerDeveloper/img/saved.png
NetkillerDeveloper/img/settings-s.png
NetkillerDeveloper/img/settings.png
NetkillerDeveloper/img/star.png
NetkillerDeveloper/js/__init__.py
NetkillerDeveloper/js/epub.js
NetkillerDeveloper/js/epub.min.js
NetkillerDeveloper/js/epub.min.map
NetkillerDeveloper/js/hooks.min.js
NetkillerDeveloper/js/hooks.min.map
NetkillerDeveloper/js/reader.js
NetkillerDeveloper/js/reader.js.map
NetkillerDeveloper/js/reader.min.js
NetkillerDeveloper/js/reader.min.map
NetkillerDeveloper/js/hooks/__init__.py
NetkillerDeveloper/js/hooks/extensions/__init__.py
NetkillerDeveloper/js/hooks/extensions/highlight.js
NetkillerDeveloper/js/libs/__init__.py
NetkillerDeveloper/js/libs/jquery.min.js
NetkillerDeveloper/js/libs/localforage.min.js
NetkillerDeveloper/js/libs/screenfull.js
NetkillerDeveloper/js/libs/screenfull.min.js
NetkillerDeveloper/js/libs/zip.min.js
NetkillerDeveloper/js/plugins/__init__.py
NetkillerDeveloper/js/plugins/hypothesis.js
NetkillerDeveloper/js/plugins/search.js
netkiller_developer-2024.3.5.0.dist-info/METADATA
netkiller_developer-2024.3.5.0.dist-info/WHEEL
netkiller_developer-2024.3.5.0.dist-info/entry_points.txt
netkiller_developer-2024.3.5.0.dist-info/top_level.txt
netkiller_developer-2024.3.5.0.dist-info/RECORD
